HCAttendanceStation/AutomatedAttendance.py
HCAttendanceStation/__init__.py
hc_attendance_station-0.0.7.dist-info/licenses/LICENSE
hc_attendance_station-0.0.7.dist-info/METADATA
hc_attendance_station-0.0.7.dist-info/WHEEL
hc_attendance_station-0.0.7.dist-info/top_level.txt
hc_attendance_station-0.0.7.dist-info/RECORD
