Metadata-Version: 2.4
Name: HC_Attendance_Station
Version: 0.0.7
Summary: Classroom attendance using a USB magstripe reader
Author-email: Joseph Deer <python@hocking.edu>
Classifier: Programming Language :: Python :: 3
Classifier: License :: OSI Approved :: MIT License
Classifier: Operating System :: Microsoft :: Windows
Requires-Python: >=3.8
License-File: LICENSE
Requires-Dist: requests
Requires-Dist: keyring
Requires-Dist: pyusb
Requires-Dist: tzdata
Requires-Dist: keyboard
Dynamic: license-file
